wbteampropy/__init__.py
wbteampropy/api.py
wbteampropy/exceptions.py
wbteampropy-0.1.0.dist-info/LICENSE
wbteampropy-0.1.0.dist-info/METADATA
wbteampropy-0.1.0.dist-info/WHEEL
wbteampropy-0.1.0.dist-info/top_level.txt
wbteampropy-0.1.0.dist-info/RECORD
