Metadata-Version: 2.1
Name: wbteampropy
Version: 0.1.0
Summary: Python interface to the WBTEAMPRO API.
Home-page: https://github.com/artphi/wbteampropy
Author: artphi
License: GPL-3
Keywords: wbteampro api library
Classifier: Programming Language :: Python :: 3
Classifier: License :: OSI Approved :: GNU General Public License v3 (GPLv3)
Classifier: Operating System :: OS Independent
License-File: LICENSE
Requires-Dist: requests (>=2.30.0)
